commons/__init__.py
commons/config.py
controller/__init__.py
controller/token_controller.py
controller/va_controller.py
model/__init__.py
model/token/__init__.py
model/token/token_b2b_request.py
model/token/token_b2b_response.py
model/va/__init__.py
model/va/additional_info.py
model/va/additional_info_response.py
model/va/create_va_request.py
model/va/create_va_response.py
model/va/total_amount.py
services/__init__.py
services/token_service.py
doku_python_library-0.0.3.dist-info/METADATA
doku_python_library-0.0.3.dist-info/WHEEL
doku_python_library-0.0.3.dist-info/top_level.txt
doku_python_library-0.0.3.dist-info/RECORD
