Metadata-Version: 2.1
Name: doku-python-library
Version: 0.0.3
Summary: DOKU python library for Payment Integration
Home-page: UNKNOWN
License: UNKNOWN
Platform: UNKNOWN
Classifier: Programming Language :: Python :: 3
Classifier: License :: OSI Approved :: MIT License
Classifier: Operating System :: OS Independent
Requires-Python: >=3.6
